COBY/__init__.py
COBY/__main__.py
COBY/citation.py
COBY/help.py
COBY/version.py
COBY/fragment_definitions/__init__.py
COBY/fragment_definitions/fragment_defs_BMP_LTF.py
COBY/fragment_definitions/fragment_defs_cardiolipins_LTF.py
COBY/fragment_definitions/fragment_defs_diglycerides_LTF.py
COBY/fragment_definitions/fragment_defs_fattyacids_LTF.py
COBY/fragment_definitions/fragment_defs_hydrocarbons_LTF.py
COBY/fragment_definitions/fragment_defs_monoglycerides_LTF.py
COBY/fragment_definitions/fragment_defs_phospholipids_LTF.py
COBY/fragment_definitions/fragment_defs_phospholipids_M3ReleaseParamters.py
COBY/fragment_definitions/fragment_defs_sphingolipid_LTF.py
COBY/fragment_definitions/fragment_defs_triglycerides_LTF.py
COBY/fragment_definitions/function_tailbuilder.py
COBY/fragment_definitions/.ipynb_checkpoints/lipid_fragment_builder-checkpoint.ipynb
COBY/general_functions/__init__.py
COBY/general_functions/center_coords.py
COBY/general_functions/dictprinter.py
COBY/general_functions/flatten.py
COBY/main_class/COBY_class.py
COBY/main_class/Crafter_class.py
COBY/main_class/Library_class.py
COBY/main_class/Misc_classes.py
COBY/main_class/__init__.py
COBY/main_class/command_preprocessors/__init__.py
COBY/main_class/command_preprocessors/memb_preprocessor.py
COBY/main_class/command_preprocessors/prot_preprocessor.py
COBY/main_class/command_preprocessors/solv_preprocessor.py
COBY/main_class/definition_preprocessors/__init__.py
COBY/main_class/definition_preprocessors/import_library.py
COBY/main_class/definition_preprocessors/ion_defs_preprocessor.py
COBY/main_class/definition_preprocessors/lipid_defs_preprocessor.py
COBY/main_class/definition_preprocessors/lipid_scaffolds_preprocessor.py
COBY/main_class/definition_preprocessors/molecule_beads_checker.py
COBY/main_class/definition_preprocessors/molecule_defs_checker.py
COBY/main_class/definition_preprocessors/solvent_defs_preprocessor.py
COBY/main_class/general_tools/__init__.py
COBY/main_class/general_tools/backupper.py
coby-1.0.10.dist-info/METADATA
coby-1.0.10.dist-info/WHEEL
coby-1.0.10.dist-info/licenses/LICENSE
coby-1.0.10.dist-info/RECORD
