Metadata-Version: 2.4
Name: COBY
Version: 1.0.10
Summary: Build coarse-grained molecular systems
Project-URL: Repository, https://github.com/MikkelDA/COBY
Author-email: "Andreasen, M.D." <mdahlandreasen@hotmail.com>
License-File: LICENSE
Keywords: building,dynamics,martini,molecular,system
Classifier: Development Status :: 5 - Production/Stable
Classifier: License :: OSI Approved :: Apache Software License
Classifier: Operating System :: OS Independent
Classifier: Programming Language :: Python :: 3
Classifier: Programming Language :: Python :: 3.9
Classifier: Programming Language :: Python :: 3.10
Classifier: Programming Language :: Python :: 3.11
Classifier: Programming Language :: Python :: 3.12
Requires-Python: >=3.9
Requires-Dist: alphashape>=1.3.1
Requires-Dist: shapely>=2.0.0
